QueryBuilderSqlAlchemy/__init__.py
QueryBuilderSqlAlchemy/query_builder.py
query_builder_sql_alchemy-0.1.3.dist-info/LICENSE
query_builder_sql_alchemy-0.1.3.dist-info/METADATA
query_builder_sql_alchemy-0.1.3.dist-info/WHEEL
query_builder_sql_alchemy-0.1.3.dist-info/RECORD
